urljoin/__init__.py
urljoin/urljoin.py
urljoin-1.0.0.dist-info/DESCRIPTION.rst
urljoin-1.0.0.dist-info/METADATA
urljoin-1.0.0.dist-info/RECORD
urljoin-1.0.0.dist-info/WHEEL
urljoin-1.0.0.dist-info/metadata.json
urljoin-1.0.0.dist-info/top_level.txt
